CHANGES.rst
CONTRIBUTORS.rst
MANIFEST.in
README.rst
bootstrap.py
buildout.cfg
setup.py
cpskin/__init__.py
cpskin.diazotheme.classic.egg-info/PKG-INFO
cpskin.diazotheme.classic.egg-info/SOURCES.txt
cpskin.diazotheme.classic.egg-info/dependency_links.txt
cpskin.diazotheme.classic.egg-info/entry_points.txt
cpskin.diazotheme.classic.egg-info/namespace_packages.txt
cpskin.diazotheme.classic.egg-info/not-zip-safe
cpskin.diazotheme.classic.egg-info/requires.txt
cpskin.diazotheme.classic.egg-info/top_level.txt
cpskin/diazotheme/__init__.py
cpskin/diazotheme/classic/__init__.py
cpskin/diazotheme/classic/configure.zcml
cpskin/diazotheme/classic/profiles.zcml
cpskin/diazotheme/classic/upgradehandlers.py
cpskin/diazotheme/classic/profiles/default/cssregistry.xml
cpskin/diazotheme/classic/profiles/default/lessregistry.xml
cpskin/diazotheme/classic/profiles/default/metadata.xml
cpskin/diazotheme/classic/profiles/default/theme.xml
cpskin/diazotheme/classic/profiles/uninstall/cssregistry.xml
cpskin/diazotheme/classic/profiles/uninstall/lessregistry.xml
cpskin/diazotheme/classic/static/manifest.cfg
cpskin/diazotheme/classic/static/preview.png
cpskin/diazotheme/classic/static/rules.xml
cpskin/diazotheme/classic/static/css/theme-styles.css
cpskin/diazotheme/classic/static/images/header-bg.jpg
cpskin/diazotheme/classic/static/less/styles.less
cpskin/diazotheme/classic/static/less/variables.less
docs/LICENSE.GPL
docs/LICENSE.rst